palworld_pal_editor/__init__.py
palworld_pal_editor/__main__.py
palworld_pal_editor/cli.py
palworld_pal_editor/config.py
palworld_pal_editor/gui.py
palworld_pal_editor/webui.py
palworld_pal_editor/api/__init__.py
palworld_pal_editor/api/auth.py
palworld_pal_editor/api/pal.py
palworld_pal_editor/api/player.py
palworld_pal_editor/api/save.py
palworld_pal_editor/assets/.DS_Store
palworld_pal_editor/assets/data/i18n_list.json
palworld_pal_editor/assets/data/old_pal_attacks.json
palworld_pal_editor/assets/data/pal_attacks.json
palworld_pal_editor/assets/data/pal_data.json
palworld_pal_editor/assets/data/pal_exp_table.json
palworld_pal_editor/assets/data/pal_passives.json
palworld_pal_editor/assets/data/update_attacks.py
palworld_pal_editor/assets/data/update_pals.py
palworld_pal_editor/assets/icons/elements/Element_Dark.png
palworld_pal_editor/assets/icons/elements/Element_Dragon.png
palworld_pal_editor/assets/icons/elements/Element_Electric.png
palworld_pal_editor/assets/icons/elements/Element_Fire.png
palworld_pal_editor/assets/icons/elements/Element_Grass.png
palworld_pal_editor/assets/icons/elements/Element_Ground.png
palworld_pal_editor/assets/icons/elements/Element_Ice.png
palworld_pal_editor/assets/icons/elements/Element_Neutral.png
palworld_pal_editor/assets/icons/elements/Element_Water.png
palworld_pal_editor/assets/icons/pals/.DS_Store
palworld_pal_editor/assets/icons/pals/Alpaca.png
palworld_pal_editor/assets/icons/pals/AmaterasuWolf.png
palworld_pal_editor/assets/icons/pals/Anubis.png
palworld_pal_editor/assets/icons/pals/Baphomet.png
palworld_pal_editor/assets/icons/pals/Baphomet_Dark.png
palworld_pal_editor/assets/icons/pals/Bastet.png
palworld_pal_editor/assets/icons/pals/Bastet_Ice.png
palworld_pal_editor/assets/icons/pals/BeardedDragon.png
palworld_pal_editor/assets/icons/pals/BerryGoat.png
palworld_pal_editor/assets/icons/pals/BirdDragon.png
palworld_pal_editor/assets/icons/pals/BirdDragon_Ice.png
palworld_pal_editor/assets/icons/pals/BlackCentaur.png
palworld_pal_editor-0.10.1.post1.dist-info/LICENSE
palworld_pal_editor-0.10.1.post1.dist-info/METADATA
palworld_pal_editor-0.10.1.post1.dist-info/WHEEL
palworld_pal_editor-0.10.1.post1.dist-info/top_level.txt
palworld_pal_editor-0.10.1.post1.dist-info/RECORD
