Metadata-Version: 2.1
Name: palworld-pal-editor
Version: 0.10.1.post1
Summary: Yet Another Palworld Pal Editor.
Author-email: _connlost <4348524953.h@gmail.com>
License: GNU GENERAL PUBLIC LICENSE
Project-URL: Homepage, https://github.com/KrisCris/Palworld-Pal-Editor
Project-URL: Documentation, https://github.com/KrisCris/Palworld-Pal-Editor
Project-URL: Repository, https://github.com/KrisCris/Palworld-Pal-Editor.git
Project-URL: Issues, https://github.com/KrisCris/Palworld-Pal-Editor/issues
Project-URL: Changelog, https://github.com/KrisCris/Palworld-Pal-Editor
Keywords: palworld,editor,pal
Classifier: Programming Language :: Python :: 3
Classifier: License :: OSI Approved :: GNU General Public License v3 (GPLv3)
Classifier: Operating System :: OS Independent
Classifier: Natural Language :: Chinese (Simplified)
Classifier: Natural Language :: English
Classifier: Natural Language :: Japanese
Requires-Python: >=3.11
License-File: LICENSE
Requires-Dist: setuptools==69.1.0
Requires-Dist: palworld-save-tools==0.24.0
Requires-Dist: wheel==0.42.0
Requires-Dist: Flask==3.0.2
Requires-Dist: pyinstaller==6.4.0
Requires-Dist: waitress==3.0.0
Requires-Dist: Flask-JWT-Extended==4.6.0
Requires-Dist: pywebview==4.4.1
Requires-Dist: requests==2.32.2
